clloader/__init__.py
clloader/loader.py
clloader/viz.py
clloader/datasets/__init__.py
clloader/datasets/base.py
clloader/datasets/fellowship.py
clloader/datasets/imagenet.py
clloader/datasets/pytorch.py
clloader/datasets/transformed.py
tests/__init__.py
tests/test_imagefolder.py
tests/test_inmemory.py
tests/test_transformed.py
clloader-0.0.2.dist-info/LICENSE
clloader-0.0.2.dist-info/METADATA
clloader-0.0.2.dist-info/WHEEL
clloader-0.0.2.dist-info/top_level.txt
clloader-0.0.2.dist-info/RECORD
